{
    "Ar36": {
        "error": 0.00017321573372366855, 
        "fit": "previous", 
        "references": [
            {
                "exclude": false, 
                "record_id": "bc-02-J-264"
            }
        ], 
        "value": 0.00481139525942036
    }, 
    "Ar37": {
        "error": 0.004725261638101363, 
        "fit": "previous", 
        "references": [
            {
                "exclude": false, 
                "record_id": "bc-02-J-264"
            }
        ], 
        "value": 0.04462580135995632
    }, 
    "Ar38": {
        "error": 0.0021259359137479577, 
        "fit": "previous", 
        "references": [
            {
                "exclude": false, 
                "record_id": "bc-02-J-264"
            }
        ], 
        "value": 0.00405289206919893
    }, 
    "Ar39": {
        "error": 0.00887784846202401, 
        "fit": "previous", 
        "references": [
            {
                "exclude": false, 
                "record_id": "bc-02-J-264"
            }
        ], 
        "value": 0.016658261516306602
    }, 
    "Ar40": {
        "error": 0.007019913145484661, 
        "fit": "previous", 
        "references": [
            {
                "exclude": false, 
                "record_id": "bc-02-J-264"
            }
        ], 
        "value": 0.20919586412483931
    }, 
    "PM41": {
        "error": 0.058613385951626, 
        "fit": "previous", 
        "references": [
            {
                "exclude": false, 
                "record_id": "bc-02-J-264"
            }
        ], 
        "value": 0.025097844483999543
    }
}