{
    "Ar36": {
        "error": 0.0004796104012651558, 
        "filter_outliers_dict": {
            "filter_outliers": true, 
            "iterations": 1, 
            "std_devs": 2
        }, 
        "fit": "Linear", 
        "value": 0.04006068037803887
    }, 
    "Ar37": {
        "error": 0.011480581318709548, 
        "filter_outliers_dict": {
            "filter_outliers": true, 
            "iterations": 1, 
            "std_devs": 2
        }, 
        "fit": "linear", 
        "value": 3.0633832208457266
    }, 
    "Ar38": {
        "error": 0.004914197201826048, 
        "filter_outliers_dict": {
            "filter_outliers": true, 
            "iterations": 1, 
            "std_devs": 2
        }, 
        "fit": "linear", 
        "value": 1.9614987373516866
    }, 
    "Ar39": {
        "error": 0.022463396787439333, 
        "filter_outliers_dict": {
            "filter_outliers": true, 
            "iterations": 1, 
            "std_devs": 2
        }, 
        "fit": "Linear", 
        "value": 154.16044365372812
    }, 
    "Ar40": {
        "error": 0.05155013958879588, 
        "filter_outliers_dict": {
            "filter_outliers": true, 
            "iterations": 1, 
            "std_devs": 2
        }, 
        "fit": "Linear", 
        "value": 646.6994493368858
    }, 
    "PM41": {
        "error": 0.06424666305307024, 
        "filter_outliers_dict": {
            "filter_outliers": false, 
            "iterations": 1, 
            "std_devs": 2
        }, 
        "fit": "linear", 
        "value": -0.11664406103223293
    }
}