{
    "Ar36": {
        "error": 0.0004472221245051585, 
        "filter_outliers_dict": {
            "filter_outliers": true, 
            "iterations": 1, 
            "std_devs": 2
        }, 
        "fit": "Linear", 
        "value": 0.03159618221274307
    }, 
    "Ar37": {
        "error": 0.011379082924789436, 
        "filter_outliers_dict": {
            "filter_outliers": true, 
            "iterations": 1, 
            "std_devs": 2
        }, 
        "fit": "linear", 
        "value": 0.06605274724739632
    }, 
    "Ar38": {
        "error": 0.005364388585587056, 
        "filter_outliers_dict": {
            "filter_outliers": true, 
            "iterations": 1, 
            "std_devs": 2
        }, 
        "fit": "linear", 
        "value": 0.2008222410171409
    }, 
    "Ar39": {
        "error": 0.011185787006511651, 
        "filter_outliers_dict": {
            "filter_outliers": true, 
            "iterations": 1, 
            "std_devs": 2
        }, 
        "fit": "Linear", 
        "value": 7.127209026829316
    }, 
    "Ar40": {
        "error": 0.013613000869110931, 
        "filter_outliers_dict": {
            "filter_outliers": true, 
            "iterations": 1, 
            "std_devs": 2
        }, 
        "fit": "Linear", 
        "value": 40.90969371024126
    }, 
    "PM41": {
        "error": 0.06517238069485115, 
        "filter_outliers_dict": {
            "filter_outliers": false, 
            "iterations": 1, 
            "std_devs": 2
        }, 
        "fit": "linear", 
        "value": -0.13382082298486234
    }
}