{
    "AX": {
        "error": 0.004899032156336802, 
        "filter_outliers_dict": {
            "filter_outliers": true, 
            "iterations": 1, 
            "std_devs": 2
        }, 
        "fit": "average", 
        "value": -0.05711800386331766
    }, 
    "CDD": {
        "error": 3.404027653031804e-06, 
        "filter_outliers_dict": {
            "filter_outliers": true, 
            "iterations": 1, 
            "std_devs": 10
        }, 
        "fit": "average", 
        "value": 9.9243607467758e-06
    }, 
    "H1": {
        "error": 0.004014832341479405, 
        "filter_outliers_dict": {
            "filter_outliers": true, 
            "iterations": 1, 
            "std_devs": 2
        }, 
        "fit": "average", 
        "value": -0.02598963351071597
    }, 
    "H2": {
        "error": 0.005655239270989311, 
        "filter_outliers_dict": {
            "filter_outliers": true, 
            "iterations": 1, 
            "std_devs": 2
        }, 
        "fit": "average", 
        "value": -0.1853105872447918
    }, 
    "L1": {
        "error": 0.001983752123693713, 
        "filter_outliers_dict": {
            "filter_outliers": true, 
            "iterations": 1, 
            "std_devs": 2
        }, 
        "fit": "average", 
        "value": -0.022920426250671245
    }, 
    "L2": {
        "error": 0.004110479427839704, 
        "filter_outliers_dict": {
            "filter_outliers": true, 
            "iterations": 1, 
            "std_devs": 2
        }, 
        "fit": "average", 
        "value": -0.030074736531882376
    }
}