{
    "Ar36": {
        "error": 0.0002690088115825466, 
        "filter_outliers_dict": {
            "filter_outliers": true, 
            "iterations": 1, 
            "std_devs": 2
        }, 
        "fit": "Linear", 
        "value": 0.009829119115903916
    }, 
    "Ar37": {
        "error": 0.009757547634378338, 
        "filter_outliers_dict": {
            "filter_outliers": true, 
            "iterations": 1, 
            "std_devs": 2
        }, 
        "fit": "linear", 
        "value": 0.6242982662191678
    }, 
    "Ar38": {
        "error": 0.0048542531860916015, 
        "filter_outliers_dict": {
            "filter_outliers": true, 
            "iterations": 1, 
            "std_devs": 2
        }, 
        "fit": "linear", 
        "value": 2.1952975237910817
    }, 
    "Ar39": {
        "error": 0.023896314687231277, 
        "filter_outliers_dict": {
            "filter_outliers": true, 
            "iterations": 1, 
            "std_devs": 2
        }, 
        "fit": "Linear", 
        "value": 163.08233793575
    }, 
    "Ar40": {
        "error": 0.04409674520927114, 
        "filter_outliers_dict": {
            "filter_outliers": true, 
            "iterations": 1, 
            "std_devs": 2
        }, 
        "fit": "Linear", 
        "value": 671.8667171240297
    }, 
    "PM41": {
        "error": 0.07657513954957497, 
        "filter_outliers_dict": {
            "filter_outliers": false, 
            "iterations": 1, 
            "std_devs": 2
        }, 
        "fit": "linear", 
        "value": -0.13135966773132182
    }
}