{
    "AX": {
        "error": 0.006527197567839871, 
        "filter_outliers_dict": {
            "filter_outliers": true, 
            "iterations": 1, 
            "std_devs": 2
        }, 
        "fit": "average", 
        "value": -0.06696338939855201
    }, 
    "CDD": {
        "error": 4.834377437439847e-06, 
        "filter_outliers_dict": {
            "filter_outliers": true, 
            "iterations": 1, 
            "std_devs": 10
        }, 
        "fit": "average", 
        "value": 9.9243607467758e-06
    }, 
    "H1": {
        "error": 0.005739546845544589, 
        "filter_outliers_dict": {
            "filter_outliers": true, 
            "iterations": 1, 
            "std_devs": 2
        }, 
        "fit": "average", 
        "value": -0.030833928545741397
    }, 
    "H2": {
        "error": 0.00894435605160945, 
        "filter_outliers_dict": {
            "filter_outliers": true, 
            "iterations": 1, 
            "std_devs": 2
        }, 
        "fit": "average", 
        "value": -0.19718227022752768
    }, 
    "L1": {
        "error": 0.0024733188360698747, 
        "filter_outliers_dict": {
            "filter_outliers": true, 
            "iterations": 1, 
            "std_devs": 2
        }, 
        "fit": "average", 
        "value": -0.020684147543091343
    }, 
    "L2": {
        "error": 0.005505360695297977, 
        "filter_outliers_dict": {
            "filter_outliers": true, 
            "iterations": 1, 
            "std_devs": 2
        }, 
        "fit": "average", 
        "value": -0.017874751952775592
    }
}