{
    "AX": {
        "error": 0.00642506056144344, 
        "filter_outliers_dict": {
            "filter_outliers": true, 
            "iterations": 1, 
            "std_devs": 2
        }, 
        "fit": "average", 
        "value": -0.06530565534561802
    }, 
    "CDD": {
        "error": 1.9054878096571286e-05, 
        "filter_outliers_dict": {
            "filter_outliers": true, 
            "iterations": 1, 
            "std_devs": 10
        }, 
        "fit": "average", 
        "value": 0.00014886541257400505
    }, 
    "H1": {
        "error": 0.004757307968269761, 
        "filter_outliers_dict": {
            "filter_outliers": true, 
            "iterations": 1, 
            "std_devs": 2
        }, 
        "fit": "average", 
        "value": -0.02250839722600476
    }, 
    "H2": {
        "error": 0.007308039495652883, 
        "filter_outliers_dict": {
            "filter_outliers": true, 
            "iterations": 1, 
            "std_devs": 2
        }, 
        "fit": "average", 
        "value": -0.21601377341390054
    }, 
    "L1": {
        "error": 0.002673091641940383, 
        "filter_outliers_dict": {
            "filter_outliers": true, 
            "iterations": 1, 
            "std_devs": 2
        }, 
        "fit": "average", 
        "value": -0.024545411364692862
    }, 
    "L2": {
        "error": 0.0069537216521925824, 
        "filter_outliers_dict": {
            "filter_outliers": true, 
            "iterations": 1, 
            "std_devs": 2
        }, 
        "fit": "average", 
        "value": -0.033414758276253675
    }
}