{
    "AX": {
        "error": 0.007122269244531389, 
        "filter_outliers_dict": {
            "filter_outliers": true, 
            "iterations": 1, 
            "std_devs": 2
        }, 
        "fit": "average", 
        "value": -0.07394414764612875
    }, 
    "CDD": {
        "error": 2.8498235850187352e-05, 
        "filter_outliers_dict": {
            "filter_outliers": true, 
            "iterations": 1, 
            "std_devs": 10
        }, 
        "fit": "average", 
        "value": 0.0003374282725361563
    }, 
    "H1": {
        "error": 0.006015023711280786, 
        "filter_outliers_dict": {
            "filter_outliers": true, 
            "iterations": 1, 
            "std_devs": 2
        }, 
        "fit": "average", 
        "value": 0.0022298849771248534
    }, 
    "H2": {
        "error": 0.006202128944020408, 
        "filter_outliers_dict": {
            "filter_outliers": true, 
            "iterations": 1, 
            "std_devs": 2
        }, 
        "fit": "average", 
        "value": -0.21046356752221632
    }, 
    "L1": {
        "error": 0.0036999203018835726, 
        "filter_outliers_dict": {
            "filter_outliers": true, 
            "iterations": 1, 
            "std_devs": 2
        }, 
        "fit": "average", 
        "value": -0.03521206725928173
    }, 
    "L2": {
        "error": 0.006904558708212096, 
        "filter_outliers_dict": {
            "filter_outliers": true, 
            "iterations": 1, 
            "std_devs": 2
        }, 
        "fit": "average", 
        "value": -0.02453638726746448
    }
}