{
    "AX": {
        "error": 0.006445538472904391, 
        "filter_outliers_dict": {
            "filter_outliers": true, 
            "iterations": 1, 
            "std_devs": 2
        }, 
        "fit": "average", 
        "value": -0.06619915068691873
    }, 
    "CDD": {
        "error": 3.8788162373273236e-05, 
        "filter_outliers_dict": {
            "filter_outliers": true, 
            "iterations": 1, 
            "std_devs": 10
        }, 
        "fit": "average", 
        "value": 0.0004714071508991621
    }, 
    "H1": {
        "error": 0.0053561580970381256, 
        "filter_outliers_dict": {
            "filter_outliers": true, 
            "iterations": 1, 
            "std_devs": 2
        }, 
        "fit": "average", 
        "value": -0.003764905707992323
    }, 
    "H2": {
        "error": 0.008145205703178192, 
        "filter_outliers_dict": {
            "filter_outliers": true, 
            "iterations": 1, 
            "std_devs": 2
        }, 
        "fit": "average", 
        "value": -0.2062218929005616
    }, 
    "L1": {
        "error": 0.003781995190421013, 
        "filter_outliers_dict": {
            "filter_outliers": true, 
            "iterations": 1, 
            "std_devs": 2
        }, 
        "fit": "average", 
        "value": -0.0292702449220573
    }, 
    "L2": {
        "error": 0.005430447861183115, 
        "filter_outliers_dict": {
            "filter_outliers": true, 
            "iterations": 1, 
            "std_devs": 2
        }, 
        "fit": "average", 
        "value": -0.019126448401748142
    }
}